tbears/__init__.py
tbears/__main__.py
tbears/tbears_cli.py
tbears/tbears_exception.py
tbears/block_manager/__init__.py
tbears/block_manager/__main__.py
tbears/block_manager/block.py
tbears/block_manager/block_manager.py
tbears/block_manager/channel_service.py
tbears/block_manager/hash_utils.py
tbears/block_manager/icon_service.py
tbears/block_manager/message_code.py
tbears/block_manager/task.py
tbears/block_manager/tbears_db.py
tbears/block_manager/tx_verifier.py
tbears/command/__init__.py
tbears/command/command.py
tbears/command/command_score.py
tbears/command/command_server.py
tbears/command/command_util.py
tbears/command/command_wallet.py
tbears/config/__init__.py
tbears/config/tbears_config.py
tbears/data/mainnet.tar.gz
tbears/libs/__init__.py
tbears/libs/icon_integrate_test.py
tbears/libs/scoretest/__init__.py
tbears/libs/scoretest/score_test_case.py
tbears/libs/scoretest/mock/__init__.py
tbears/libs/scoretest/mock/block.py
tbears/libs/scoretest/mock/db.py
tbears/libs/scoretest/mock/icx_engine.py
tbears/libs/scoretest/patch/__init__.py
tbears/libs/scoretest/patch/context.py
tbears/libs/scoretest/patch/score_patcher.py
tbears/profile_tbears/__init__.py
tbears/profile_tbears/startup/00_first.py
tbears/profile_tbears/startup/__init__.py
tbears/tools/__init__.py
tbears/tools/mainnet/__init__.py
tbears/tools/mainnet/sync.py
tbears/util/__init__.py
tbears/util/arg_parser.py
tbears/util/argparse_type.py
tbears/util/keystore_manager.py
tbears/util/transaction_logger.py
tbears-1.8.0.dist-info/METADATA
tbears-1.8.0.dist-info/WHEEL
tbears-1.8.0.dist-info/entry_points.txt
tbears-1.8.0.dist-info/top_level.txt
tbears-1.8.0.dist-info/RECORD
