Metadata-Version: 2.1
Name: tbears
Version: 1.8.0
Summary: Test suite for ICON SCORE development
Home-page: https://github.com/icon-project/t-bears
Author: ICON Foundation
Author-email: foo@icon.foundation
License: Apache License 2.0
Platform: UNKNOWN
Classifier: Development Status :: 5 - Production/Stable
Classifier: Intended Audience :: Developers
Classifier: Intended Audience :: System Administrators
Classifier: Natural Language :: English
Classifier: License :: OSI Approved :: Apache Software License
Classifier: Programming Language :: Python :: 3.7
Requires-Python: >=3.7, <3.8
Requires-Dist: iconrpcserver (~=1.6.0)
Requires-Dist: iconservice (~=1.8.9)
Requires-Dist: iconsdk (~=1.3.4)
Requires-Dist: ipython (>=6.4.0)
